Autoclose.py
AkerAutoSetup-0.1.dist-info/LICENSE.txt
AkerAutoSetup-0.1.dist-info/METADATA
AkerAutoSetup-0.1.dist-info/WHEEL
AkerAutoSetup-0.1.dist-info/top_level.txt
AkerAutoSetup-0.1.dist-info/RECORD
