Metadata-Version: 2.1
Name: AkerAutoSetup
Version: 0.1
Summary: AutoClose for Sunstates Aker
Home-page: http://github.com/example
Author: Matthew Turner
Author-email: MatthewT@example.com
License: MIT
Platform: UNKNOWN
Requires-Dist: pyautogui
Requires-Dist: pywin32
